rpcompletion/__init__.py
rpcompletion/__main__.py
rpcompletion/rpCofactors.py
rpcompletion/rpCompletion.py
rpcompletion-1.2.0.dist-info/LICENSE
rpcompletion-1.2.0.dist-info/METADATA
rpcompletion-1.2.0.dist-info/WHEEL
rpcompletion-1.2.0.dist-info/top_level.txt
rpcompletion-1.2.0.dist-info/RECORD
