Metadata-Version: 2.1
Name: rpcompletion
Version: 1.2.0
Summary: 'pathway completion'
Home-page: https://github.com/brsynth/rpcompletion
Author: 'melchior du lac, joan hérisson'
Author-email: joan.herisson@univ-evry.fr
License: MIT
Platform: UNKNOWN
Classifier: Programming Language :: Python :: 3
Classifier: License :: OSI Approved :: MIT License
Classifier: Operating System :: OS Independent
Requires-Python: >=3.5
Requires-Dist: brs-utils
Requires-Dist: brs-libs
Requires-Dist: credisdict
Requires-Dist: requests
Requires-Dist: urllib3
